saudacoes/__init__.py
saudacoes_simples-0.1.dist-info/LICENSE
saudacoes_simples-0.1.dist-info/METADATA
saudacoes_simples-0.1.dist-info/WHEEL
saudacoes_simples-0.1.dist-info/top_level.txt
saudacoes_simples-0.1.dist-info/RECORD
