Metadata-Version: 2.1
Name: saudacoes_simples
Version: 0.1
Summary: Um pacote simples para dizer olá e adeus
Home-page: https://github.com/AlaiSeide/pacotes-pypi.git
Author: Alai Seide
Author-email: tenw313@gmail.com
Classifier: Programming Language :: Python :: 3
Classifier: License :: OSI Approved :: MIT License
Classifier: Operating System :: OS Independent
Requires-Python: >=3.6
License-File: LICENSE
